flask_lambda.py
flask_lambda_python37-0.0.1.dist-info/LICENSE
flask_lambda_python37-0.0.1.dist-info/METADATA
flask_lambda_python37-0.0.1.dist-info/WHEEL
flask_lambda_python37-0.0.1.dist-info/top_level.txt
flask_lambda_python37-0.0.1.dist-info/RECORD
