Metadata-Version: 2.1
Name: flask-lambda-python37
Version: 0.0.1
Summary: Python3.7+ module to make Flask compatible with AWS Lambda
Home-page: https://github.com/caprasadrajmane/flask-lambda
Author: Prasad Rajmane
Author-email: caprasadrajmane@gmail.com
License: Apache License, Version 2.0
Keywords: flask aws amazon lambda
Platform: UNKNOWN
Classifier: Development Status :: 5 - Production/Stable
Classifier: Programming Language :: Python
Classifier: Environment :: Console
Classifier: Operating System :: POSIX
Classifier: Programming Language :: Python :: 3.7
Classifier: Intended Audience :: Developers
Classifier: Natural Language :: English
Classifier: License :: OSI Approved :: Apache Software License
Requires-Dist: Flask (>=2.2.2)
